LICENSE.txt
MANIFEST.in
README.md
setup.py
codereef/__init__.py
codereef/__main__.py
codereef/client.py
codereef/comm.py
codereef/config.py
codereef/graph.py
codereef/main.py
codereef/misc.py
codereef/obj.py
codereef/setup.py
codereef/solution.py
codereef.egg-info/PKG-INFO
codereef.egg-info/SOURCES.txt
codereef.egg-info/dependency_links.txt
codereef.egg-info/entry_points.txt
codereef.egg-info/not-zip-safe
codereef.egg-info/requires.txt
codereef.egg-info/top_level.txt
codereef/static/favicon.ico