Metadata-Version: 1.2
Name: codereef
Version: 0.7.25
Summary: CodeReef client to deal with portable workflows
Home-page: https://codereef.ai/portal
Author: Grigori Fursin
Author-email: Grigori.Fursin@CodeReef.ai
License: Apache Software License (Apache 2.0)
Keywords: portable workflows,reproducibility,collaborative experiments,portability,dependencies,workflows,automation,pipelines,data pipelines,computer systems,data science
Platform: UNKNOWN
Classifier: Development Status :: 4 - Beta
Classifier: Programming Language :: Python :: 2.7
Classifier: Programming Language :: Python :: 3
Classifier: Intended Audience :: Developers
Classifier: Intended Audience :: Education
Classifier: Intended Audience :: End Users/Desktop
Classifier: Intended Audience :: Information Technology
Classifier: Intended Audience :: Science/Research
Requires-Python: >=2.7
